README.md
setup.py
ethango_numbergame/Error.py
ethango_numbergame/MainGame.py
ethango_numbergame/Player.py
ethango_numbergame.egg-info/PKG-INFO
ethango_numbergame.egg-info/SOURCES.txt
ethango_numbergame.egg-info/dependency_links.txt
ethango_numbergame.egg-info/not-zip-safe
ethango_numbergame.egg-info/top_level.txt