Metadata-Version: 1.0
Name: ethango-numbergame
Version: 0.1
Summary: Number guessing game
Home-page: UNKNOWN
Author: UNKNOWN
Author-email: UNKNOWN
License: UNKNOWN
Platform: UNKNOWN
